[ 
  {
    "game": "Wisconsin 79 | UNC 72",
    "efg": "53.6",
    "to": "6.7",
    "or": "28.1",
    "ft": "32.1",
    "ppp": "1.20",
    "oefg": "52.7",
    "oto": "8.4",
    "oor": "38.7",
    "oft": "41.2",
    "oppp": "1.32",
    "result": "loss",
    "style": "ffbfb2",
    "box": "/boxes/2015/wisco-79-unc-72/"
  },
  {
    "game": "UNC 87 | Arkansas 78",
    "efg": "48.3",
    "to": "20.6",
    "or": "47.2",
    "ft": "61.7",
    "ppp": "1.12",
    "oefg": "43.1",
    "oto": "27.0",
    "oor": "44.4",
    "oft": "41.5",
    "oppp": "1.00",
    "result": "win",
    "style": "99ffb2",
    "box": "/boxes/2015/unc-87-ark-78/"
  },
  {
    "game": "UNC 67 | Harvard 65",
    "efg": "60.2",
    "to": "28.4",
    "or": "46.2",
    "ft": "26.5",
    "ppp": "1.12",
    "oefg": "42.7",
    "oto": "11.7",
    "oor": "34.3",
    "oft": "36.4",
    "oppp": "1.08",
    "result": "win",
    "style": "99ffb2",
    "box": "/boxes/2015/unc-67-harvard-65/"
  },
  {
    "game": "Notre Dame 90 | UNC 82",
    "efg": "58.3",
    "to": "18.9",
    "or": "41.9",
    "ft": "10.6",
    "ppp": "1.19",
    "oefg": "64.6",
    "oto": "18.9",
    "oor": "34.8",
    "oft": "66.7",
    "oppp": "1.30",
    "result": "loss",
    "style": "ffbfb2",
    "box": "/boxes/2015/nd-90-unc-82/"
  },
  {
    "game": "UNC 71 | UVA 67",
    "efg": "63.1",
    "to": "27.0",
    "or": "28.0",
    "ft": "64.3",
    "ppp": "1.06",
    "oefg": "49.0",
    "oto": "19.5",
    "oor": "21.9",
    "oft": "38.5",
    "oppp": "1.00",
    "result": "win",
    "style": "99ffb2",
    "box": "/boxes/2015/unc-71-uva-67/"
  },
  {
    "game": "UNC 70 | Louisville 60",
    "efg": "46.6",
    "to": "17.2",
    "or": "30.3",
    "ft": "28.8",
    "ppp": "1.00",
    "oefg": "38.1",
    "oto": "18.6",
    "oor": "34.9",
    "oft": "31.8",
    "oppp": "0.86",
    "result": "win",
    "style": "99ffb2",
    "box": "/boxes/2015/unc-70-lville-60/"
  },
  {
    "game": "UNC 81 | Boston College 63",
    "efg": "53.1",
    "to": "11.9",
    "or": "38.2",
    "ft": "24.6",
    "ppp": "1.21",
    "oefg": "43.4",
    "oto": "10.4",
    "oor": "11.8",
    "oft": "41.5",
    "oppp": "0.94",
    "result": "win",
    "style": "99ffb2",
    "box": "/boxes/2015/unc-81-bc-63/"
  },
  {
    "game": "Duke 84 | UNC 77",
    "efg": "55.2",
    "to": "23.4",
    "or": "37.9",
    "ft": "22.4",
    "ppp": "1.13",
    "oefg": "53.4",
    "oto": "14.6",
    "oor": "40.0",
    "oft": "44.1",
    "oppp": "1.24",
    "result": "loss",
    "style": "ffbfb2",
    "box": "/boxes/2015/duke-84-unc-77/"
  },
  {
    "game": "UNC 81 | Georgia Tech 49",
    "efg": "57.8",
    "to": "15.9",
    "or": "33.3",
    "ft": "17.2",
    "ppp": "1.17",
    "oefg": "33.6",
    "oto": "26.0",
    "oor": "36.4",
    "oft": "32.8",
    "oppp": "0.71",
    "result": "win",
    "style": "99ffb2",
    "box": "/boxes/2015/unc-81-gt-49/"
  },
  {
    "game": "UNC 73 | Miami 64",
    "efg": "49.1",
    "to": "21.1",
    "or": "33.3",
    "ft": "36.8",
    "ppp": "1.03",
    "oefg": "48.2",
    "oto": "18.3",
    "oor": "16.2",
    "oft": "26.3",
    "oppp": "0.90",
    "result": "win",
    "style": "99ffb2",
    "box": "/boxes/2015/unc-73-miami-64/"
  },
  {
    "game": "NCSU 58 | UNC 46",
    "efg": "37.3",
    "to": "19.9",
    "or": "28.2",
    "ft": "16.4",
    "ppp": "0.77",
    "oefg": "41.2",
    "oto": "14.9",
    "oor": "32.5",
    "oft": "28.1",
    "oppp": "0.97",
    "result": "loss",
    "style": "ffbfb2",
    "box": "/boxes/2015/state-58-unc-46/"
  },
  {
    "game": "UNC 89 | Georgia Tech 60",
    "efg": "66.4",
    "to": "11.8",
    "or": "28.0",
    "ft": "18.0",
    "ppp": "1.31",
    "oefg": "43.3",
    "oto": "16.2",
    "oor": "26.8",
    "oft": "28.3",
    "oppp": "0.88",
    "result": "win",
    "style": "99ffb2",
    "box": "/boxes/2015/unc-89-gt-60/"
  },
  {
    "game": "Duke 92 | UNC 90 (OT)",
    "efg": "47.0",
    "to": "13.2",
    "or": "36.5",
    "ft": "24.1",
    "ppp": "1.07",
    "oefg": "58.5",
    "oto": "19.1",
    "oor": "30.2",
    "oft": "47.7",
    "oppp": "1.10",
    "result": "loss",
    "style": "ffbfb2",
    "box": "/boxes/2015/duke-92-unc-90/"
  },
  {
    "game": "Pittsburgh 89 | UNC 76",
    "efg": "52.5",
    "to": "6.4",
    "or": "36.4",
    "ft": "39.0",
    "ppp": "1.23",
    "oefg": "71.9",
    "oto": "8.1",
    "oor": "24.0",
    "oft": "22.8",
    "oppp": "1.44",
    "result": "loss",
    "style": "ffbfb2",
    "box": "/boxes/2015/pitt-89-unc-76/"
  },
  {
    "game": "UNC 79 | Boston College 68",
    "efg": "57.8",
    "to": "20.8",
    "or": "42.9",
    "ft": "52.9",
    "ppp": "1.18",
    "oefg": "49.1",
    "oto": "16.3",
    "oor": "21.9",
    "oft": "33.9",
    "oppp": "1.01",
    "result": "win",
    "style": "99ffb2",
    "box": "/boxes/2015/unc-79-bc-68/"
  },
  {
    "game": "UVA 75 | UNC 64",
    "efg": "48.2",
    "to": "20.2",
    "or": "36.7",
    "ft": "23.2",
    "ppp": "1.00",
    "oefg": "56.3",
    "oto": "12.4",
    "oor": "25.8",
    "oft": "32.1",
    "oppp": "1.17",
    "result": "loss",
    "style": "ffbfb2",
    "box": "/boxes/2015/uva-75-unc-64/"
  },
  {
    "game": "Louisville 78 | UNC 68",
    "efg": "47.5",
    "to": "25.3",
    "or": "35.1",
    "ft": "33.3",
    "ppp": "0.91",
    "oefg": "39.2",
    "oto": "14.6",
    "oor": "41.5",
    "oft": "67.7",
    "oppp": "1.04",
    "result": "loss",
    "style": "ffbfb2",
    "box": "/boxes/2015/lville-78-unc-68/"
  },
  {
    "game": "UNC 93 | Syracuse 83",
    "efg": "63.4",
    "to": "25.1",
    "or": "39.3",
    "ft": "53.6",
    "ppp": "1.16",
    "oefg": "47.8",
    "oto": "13.8",
    "oor": "24.4",
    "oft": "33.8",
    "oppp": "1.04",
    "result": "win",
    "style": "99ffb2",
    "box": "/boxes/2015/unc-93-cuse-83/"
  },
  {
    "game": "UNC 78 | Florida State 74",
    "efg": "50.0",
    "to": "7.4",
    "or": "33.3",
    "ft": "46.7",
    "ppp": "1.16",
    "oefg": "50.8",
    "oto": "14.9",
    "oor": "31.4",
    "oft": "27.9",
    "oppp": "1.10",
    "result": "win",
    "style": "99ffb2",
    "box": "/boxes/2015/unc-78-fsu-74/"
  },
  {
    "game": "UNC 87 | Wake Forest 71",
    "efg": "62.9",
    "to": "16.3",
    "or": "25.0",
    "ft": "37.9",
    "ppp": "1.19",
    "oefg": "45.8",
    "oto": "19.1",
    "oor": "31.0",
    "oft": "43.3",
    "oppp": "0.97",
    "result": "win",
    "style": "99ffb2",
    "box": "/boxes/2015/unc-87-wake-71/"
  },
  {
    "game": "UNC 68 | Virginia Tech 63",
    "efg": "48.3",
    "to": "24.9",
    "or": "47.1",
    "ft": "28.8",
    "ppp": "1.00",
    "oefg": "40.9",
    "oto": "20.6",
    "oor": "10.8",
    "oft": "20.8",
    "oppp": "0.78",
    "result": "win",
    "style": "99ffb2",
    "box": "/boxes/2015/unc-68-vt-63/"
  },
  {
    "game": "UNC 81 | NCSU 79",
    "efg": "60.2",
    "to": "18.9",
    "or": "32.1",
    "ft": "42.3",
    "ppp": "1.17",
    "oefg": "47.7",
    "oto": "14.6",
    "oor": "42.9",
    "oft": "33.3",
    "oppp": "1.14",
    "result": "win",
    "style": "99ffb2",
    "box": "/boxes/2015/unc-81-state-79/"
  },
  {
    "game": "UNC 72 | Louisville 71",
    "efg": "47.0",
    "to": "18.0",
    "or": "44.7",
    "ft": "16.4",
    "ppp": "1.07",
    "oefg": "52.5",
    "oto": "16.5",
    "oor": "28.1",
    "oft": "18.6",
    "oppp": "1.06",
    "result": "win",
    "style": "99ffb2",
    "box": "/boxes/2015/unc-72-lville-71/"
  },
  {
    "game": "Notre Dame 71 | UNC 70",
    "efg": "40.0",
    "to": "11.3",
    "or": "51.2",
    "ft": "38.5",
    "ppp": "1.13",
    "oefg": "56.0",
    "oto": "12.9",
    "oor": "21.4",
    "oft": "38.0",
    "oppp": "1.15",
    "result": "loss",
    "style": "ffbfb2",
    "box": "/boxes/2015/nd-71-unc-70/"
  },
  {
    "game": "UNC 74 | Clemson 50",
    "efg": "48.4",
    "to": "9.8",
    "or": "44.4",
    "ft": "27.0",
    "ppp": "1.21",
    "oefg": "34.0",
    "oto": "13.1",
    "oor": "23.3",
    "oft": "39.6",
    "oppp": "0.82",
    "result": "win",
    "style": "99ffb2",
    "box": "/boxes/2015/unc-74-clem-50/"
  },
  {
    "game": "UNC 86 | William & Mary 64",
    "efg": "57.4",
    "to": "16.9",
    "or": "36.4",
    "ft": "37.7",
    "ppp": "1.21",
    "oefg": "44.3",
    "oto": "18.3",
    "oor": "17.9",
    "oft": "45.3",
    "oppp": "0.90",
    "result": "win",
    "style": "99ffb2",
    "box": "/boxes/2015/unc-86-bill-and-mary-64/"
  },
  {
    "game": "UNC 89 | UAB 58",
    "efg": "55.8",
    "to": "23.5",
    "or": "45.5",
    "ft": "51.7",
    "ppp": "1.03",
    "oefg": "33.1",
    "oto": "23.5",
    "oor": "34.1",
    "oft": "47.5",
    "oppp": "0.75",
    "result": "win",
    "style": "99ffb2",
    "box": "/boxes/2015/unc-89-uab-58/"
  },
  {
    "game": "UNC 82 | Ohio State 74",
    "efg": "46.9",
    "to": "19.5",
    "or": "40.9",
    "ft": "50.8",
    "ppp": "1.06",
    "oefg": "41.7",
    "oto": "13.0",
    "oor": "28.6",
    "oft": "25.0",
    "oppp": "0.96",
    "result": "win",
    "style": "99ffb2",
    "box": "/boxes/2015/unc-82-osu-74/"
  },
  {
    "game": "UNC 79 | UNCG 56",
    "efg": "51.6",
    "to": "24.3",
    "or": "55.6",
    "ft": "37.7",
    "ppp": "1.13",
    "oefg": "40.2",
    "oto": "18.5",
    "oor": "24.4",
    "oft": "46.4",
    "oppp": "0.80",
    "result": "win",
    "style": "99ffb2",
    "box": "/boxes/2015/unc-79-uncg-56/"
  },
  {
    "game": "Kentucky 84 | UNC 70",
    "efg": "50.0",
    "to": "28.5",
    "or": "58.1",
    "ft": "20.0",
    "ppp": "1.04",
    "oefg": "63.5",
    "oto": "22.5",
    "oor": "45.8",
    "oft": "64.6",
    "oppp": "1.25",
    "result": "loss",
    "style": "ffbfb2",
    "box": "/boxes/2015/kentucky-84-unc-70/"
  },
  {
    "game": "UNC 108 | ECU 64",
    "efg": "60.7",
    "to": "10.4",
    "or": "48.4",
    "ft": "29.3",
    "ppp": "1.40",
    "oefg": "36.2",
    "oto": "13.0",
    "oor": "26.5",
    "oft": "27.5",
    "oppp": "0.83",
    "result": "win",
    "style": "99ffb2",
    "box": "/boxes/2015/unc-108-ecu-64/"
  },
  {
    "game": "Iowa 60 | UNC 55",
    "efg": "30.9",
    "to": "16.2",
    "or": "49.0",
    "ft": "25.0",
    "ppp": "0.89",
    "oefg": "35.5",
    "oto": "19.4",
    "oor": "43.6",
    "oft": "43.6",
    "oppp": "0.97",
    "result": "loss",
    "style": "ffbfb2",
    "box": "/boxes/2015/iowa-60-unc-55/"
  },
  {
    "game": "UNC 75 | Florida 64",
    "efg": "51.0",
    "to": "27.4",
    "or": "44.1",
    "ft": "60.8",
    "ppp": "1.09",
    "oefg": "37.7",
    "oto": "23.1",
    "oor": "43.2",
    "oft": "37.7",
    "oppp": "0.93",
    "result": "win",
    "style": "99ffb2",
    "box": "/boxes/2015/unc-75-fla-64/"
  },
  {
    "game": "UNC 78 | UCLA 56",
    "efg": "47.8",
    "to": "14.9",
    "or": "31.0",
    "ft": "28.4",
    "ppp": "1.05",
    "oefg": "39.8",
    "oto": "31.1",
    "oor": "29.0",
    "oft": "75.0",
    "oppp": "0.76",
    "result": "win",
    "style": "99ffb2",
    "box": "/boxes/2015/unc-78-ucla-56/"
  },
  {
    "game": "Butler 74 | UNC 66",
    "efg": "42.1",
    "to": "24.8",
    "or": "33.3",
    "ft": "56.1",
    "ppp": "0.86",
    "oefg": "36.8",
    "oto": "24.8",
    "oor": "52.7",
    "oft": "40.3",
    "oppp": "0.96",
    "result": "loss",
    "style": "ffbfb2",
    "box": "/boxes/2015/butler-74-unc-66/"
  },
  {
    "game": "UNC 90 | Davidson 72",
    "efg": "52.2",
    "to": "12.3",
    "or": "41.9",
    "ft": "40.6",
    "ppp": "1.23",
    "oefg": "41.2",
    "oto": "13.7",
    "oor": "34.0",
    "oft": "17.6",
    "oppp": "0.99",
    "result": "win",
    "style": "99ffb2",
    "box": "/boxes/2015/unc-90-davidson-72/"
  },
  {
    "game": "UNC 103 | Robert Morris 59",
    "efg": "53.5",
    "to": "10.8",
    "or": "52.6",
    "ft": "50.7",
    "ppp": "1.39",
    "oefg": "41.0",
    "oto": "24.2",
    "oor": "31.0",
    "oft": "23.0",
    "oppp": "0.80",
    "result": "win",
    "style": "99ffb2",
    "box": "/boxes/2015/unc-103-rm-59/"
  },
  {
    "game": "UNC 76 | NCCU 60",
    "efg": "45.9",
    "to": "19.2",
    "or": "45.7",
    "ft": "49.2",
    "ppp": "1.04",
    "oefg": "36.6",
    "oto": "19.2",
    "oor": "25.0",
    "oft": "51.8",
    "oppp": "0.82",
    "result": "win",
    "style": "99ffb2",
    "box": "/boxes/2015/unc-76-nccu-60/"
  }
]